poseidon/__init__.py
poseidon/hash.py
poseidon/parameters.py
poseidon/round_constants.py
poseidon/round_numbers.py
poseidon/poseidon_hash.egg-info/SOURCES.txt
poseidon/poseidon_hash.egg-info/dependency_links.txt
poseidon/poseidon_hash.egg-info/requires.txt
poseidon/poseidon_hash.egg-info/top_level.txt
poseidon_hash-0.1.4.dist-info/LICENSE
poseidon_hash-0.1.4.dist-info/METADATA
poseidon_hash-0.1.4.dist-info/WHEEL
poseidon_hash-0.1.4.dist-info/top_level.txt
poseidon_hash-0.1.4.dist-info/RECORD
