Metadata-Version: 2.1
Name: poseidon-hash
Version: 0.1.4
Summary: Reference implementation in Python of Poseidon and optimized Poseidon (Neptune) hash functions
Home-page: https://github.com/ingonyama-zk/poseidon-hash
Author: Ingonyama
Author-email: ekaterina@ingonyama.com
Keywords: Hash Function,Cryptography
Classifier: Programming Language :: Python :: 3
Classifier: License :: OSI Approved :: MIT License
License-File: LICENSE
Requires-Dist: pytest ~=7.1.2
Requires-Dist: galois ~=0.3.6
Requires-Dist: numpy >=1.18.4
Requires-Dist: setuptools >=42.0
